unibit_api_v1/__init__.py
unibit_api_v1/companyinfo.py
unibit_api_v1/news.py
unibit_api_v1/setup.py
unibit_api_v1/stockprice.py
unibit_api_v1/test.py
unibit_api_v1/unibit.py
unibit_api_v2/__init__.py
unibit_api_v2/company.py
unibit_api_v2/corporate.py
unibit_api_v2/crypto.py
unibit_api_v2/forex.py
unibit_api_v2/news.py
unibit_api_v2/reference.py
unibit_api_v2/stock.py
unibit_api_v2/unibit.py
python_unibit-2.1.0.dist-info/LICENSE
python_unibit-2.1.0.dist-info/METADATA
python_unibit-2.1.0.dist-info/WHEEL
python_unibit-2.1.0.dist-info/top_level.txt
python_unibit-2.1.0.dist-info/RECORD
