Metadata-Version: 2.1
Name: python-unibit
Version: 2.1.0
Summary: Python SDK for the UniBit API
Home-page: https://github.com/unibit-api/python-unibit
Author: UniBit
Author-email: support@unibit.ai
License: UNKNOWN
Platform: UNKNOWN
Classifier: Programming Language :: Python :: 3
Classifier: License :: OSI Approved :: MIT License
Classifier: Operating System :: OS Independent
Requires-Dist: requests
